Workbook

Sheet 1. Exec One-Pager
B2: IF I AWAKEN IN LOS ANGELES
B3: Immersive theatre · 30,100 sq ft · 150-cap · 60-week Los Angeles run
B5: THE ASK | E5: KEY METRICS
B6: ='Production Budget'!F263 -> 6047850.3 | E6: Weekly Ticket Gross (100%) | F6: ='Seating Plan'!F26 -> 163000
E7: Weekly Operating Cost | F7: ='Weekly Operating'!F124 -> 135757
E8: Weekly Contribution @ 100% (incl F&B) | F8: ='Seating Plan'!F26+'Seating Plan'!G57-'Weekly Operating'!F124 -> 44073
B9: Total Capitalization Required | E9: Breakeven Capacity | F9: =Recoupment!C28 -> 0.74806791
E10: Avg Ticket Price (weighted) | F10: ='Seating Plan'!F26/'Seating Plan'!C9 -> 90.555556
B12: CAPITALIZATION BREAKDOWN | E12: WEEKLY OPERATING COSTS
B13: Scenic / Physical Production | C13: ='Production Budget'!F40 -> 2314250 | E13: Physical Maintenance | F13: ='Weekly Operating'!F21 -> 9300
B14: Creative & Management Fees | C14: ='Production Budget'!F90 -> 1008879 | E14: Fees (GM, PR, Marketing, Legal) | F14: ='Weekly Operating'!F37 -> 8400
B15: Pre-Opening Salaries | C15: ='Production Budget'!F135 -> 394919.48 | E15: Weekly Salaries (all staff) | F15: ='Weekly Operating'!F84 -> 81007
B16: Casting & Rehearsal | C16: ='Production Budget'!F150 -> 53500 | E16: Weekly Advertising | F16: ='Weekly Operating'!F97 -> 25500
B17: Music | C17: ='Production Budget'!F166 -> 51400 | E17: Venue & Tech (rent, utilities, CC) | F17: ='Weekly Operating'!F110 -> 8400
B18: Advertising & Launch | C18: ='Production Budget'!F187 -> 775500 | E18: General & Administrative | F18: ='Weekly Operating'!F122 -> 3150
B19: Venue Load-In & Tech Labor | C19: ='Production Budget'!F210 -> 190793.6
B20: General & Administrative | C20: ='Production Budget'!F225 -> 174700
B21: Developmental | C21: ='Production Budget'!F233 -> 75000 | E21: TOTAL WEEKLY OPERATING | F21: ='Weekly Operating'!F124 -> 135757
B22: Subtotal: Production Costs | C22: ='Production Budget'!F235 -> 5038942.1
B23: Bonds, Deposits, Advances | C23: ='Production Budget'!F252 -> 233500
B24: Reserve & 10% Contingency | C24: ='Production Budget'!F261 -> 775408.21
B25: TOTAL CAPITALIZATION | C25: ='Production Budget'!F263 -> 6047850.3
B27: RECOUPMENT AT CAPACITY SCENARIOS
B28: Capacity | C28: 100% | D28: 90% | E28: 80% | F28: 75%
B29: Weekly Contribution | C29: =('Seating Plan'!F26*1+'Seating Plan'!G57*1)-(('Weekly Operating'!F124-0.03*'Seating Plan'!F26)+0.03*1*'Seating Plan'!F26) -> 44073 | D29: =('Seating Plan'!F26*0.9+'Seating Plan'!G57*0.9)-(('Weekly Operating'!F124-0.03*'Seating Plan'!F26)+0.03*0.9*'Seating Plan'!F26) -> 26579 | E29: =('Seating Plan'!F26*0.8+'Seating Plan'!G57*0.8)-(('Weekly Operating'!F124-0.03*'Seating Plan'!F26)+0.03*0.8*'Seating Plan'!F26) -> 9085 | F29: =('Seating Plan'!F26*0.75+'Seating Plan'!G57*0.75)-(('Weekly Operating'!F124-0.03*'Seating Plan'!F26)+0.03*0.75*'Seating Plan'!F26) -> 338
B30: Weeks to Recoup | C30: =IF(('Seating Plan'!F26*1+'Seating Plan'!G57*1)-(('Weekly Operating'!F124-0.03*'Seating Plan'!F26)+0.03*1*'Seating Plan'!F26)>0,'Production Budget'!F263/(('Seating Plan'!F26*1+'Seating Plan'!G57*1)-(('Weekly Operating'!F124-0.03*'Seating Plan'!F26)+0.03*1*'Seating Plan'!F26)),"—") -> 137.22348 | D30: =IF(('Seating Plan'!F26*0.9+'Seating Plan'!G57*0.9)-(('Weekly Operating'!F124-0.03*'Seating Plan'!F26)+0.03*0.9*'Seating Plan'!F26)>0,'Production Budget'!F263/(('Seating Plan'!F26*0.9+'Seating Plan'!G57*0.9)-(('Weekly Operating'!F124-0.03*'Seating Plan'!F26)+0.03*0.9*'Seating Plan'!F26)),"—") -> 227.54243 | E30: =IF(('Seating Plan'!F26*0.8+'Seating Plan'!G57*0.8)-(('Weekly Operating'!F124-0.03*'Seating Plan'!F26)+0.03*0.8*'Seating Plan'!F26)>0,'Production Budget'!F263/(('Seating Plan'!F26*0.8+'Seating Plan'!G57*0.8)-(('Weekly Operating'!F124-0.03*'Seating Plan'!F26)+0.03*0.8*'Seating Plan'!F26)),"—") -> 665.69623 | F30: =IF(('Seating Plan'!F26*0.75+'Seating Plan'!G57*0.75)-(('Weekly Operating'!F124-0.03*'Seating Plan'!F26)+0.03*0.75*'Seating Plan'!F26)>0,'Production Budget'!F263/(('Seating Plan'!F26*0.75+'Seating Plan'!G57*0.75)-(('Weekly Operating'!F124-0.03*'Seating Plan'!F26)+0.03*0.75*'Seating Plan'!F26)),"—") -> 17893.048
B32: Run length: 60 performance weeks. 12 shows/week at 150 capacity. Tiered pricing with community-access tier on every performance.
B33: Not modeled: bar + gift shop + concessions revenue — conservatively adds 15–25% to weekly gross.

Sheet 2. Investor Summary
B2: IF I AWAKEN IN LOS ANGELES
B3: Investor Summary · Confidential
B5: THE OPPORTUNITY
B6: An immersive theatrical journey through six LA neighborhoods in a transformed 30,100 sq ft warehouse.
B7: 60-week run June 2026–August 2027. 12 shows/week. 150-capacity per show.
B9: THE ASK
B10: Total Capitalization | F10: Weekly Gross Potential
B11: ='Production Budget'!F263 -> 6047850.3 | F11: ='Seating Plan'!F26 -> 163000
B13: USE OF FUNDS
B14: Category | C14: Amount | D14: % of Total | E14: What it covers
B15: Build-out & Physical Production | C15: ='Production Budget'!F40 -> 2314250 | D15: =C15/'Production Budget'!F263 -> 0.38265663 | E15: Scenic for 6 environments, LED wall, sound/lighting install, lobby bar/shop, exterior mural
B16: Creative & Management Fees | C16: ='Production Budget'!F90 -> 1008879 | D16: =C16/'Production Budget'!F263 -> 0.16681613 | E16: Director, writer, designers, producers, GM, production manager, union benefits
B17: Pre-Opening Salaries | C17: ='Production Budget'!F135 -> 394919.48 | D17: =C17/'Production Budget'!F263 -> 0.065299149 | E17: 6-week rehearsal+tech+preview period: cast, musicians, SMs, crew
B18: Launch Marketing & Press | C18: ='Production Budget'!F187 -> 775500 | D18: =C18/'Production Budget'!F263 -> 0.12822738 | E18: Pre-opening ad spend, PR, opening night, community partner outreach
B19: Load-In Labor & Venue | C19: ='Production Budget'!F210 -> 190793.6 | D19: =C19/'Production Budget'!F263 -> 0.031547342 | E19: Scenic/electrics/audio load-in, 3-month pre-opening warehouse rent
B20: Casting, Music, Development | C20: ='Production Budget'!F150+'Production Budget'!F166+'Production Budget'!F233 -> 179900 | D20: =C20/'Production Budget'!F263 -> 0.029746107 | E20: Audition space, re-orch, music copying, site-specific R&D
B21: G&A, Legal, Insurance | C21: ='Production Budget'!F225 -> 174700 | D21: =C21/'Production Budget'!F263 -> 0.028886297 | E21: LLC formation, immersive insurance, accounting, travel/housing
B22: Bonds, Deposits, Advances | C22: ='Production Budget'!F252 -> 233500 | D22: =C22/'Production Budget'!F263 -> 0.03860876 | E22: AEA/AFM/SDC/USA bonds, LED vendor deposit, creative advances
B23: Reserve (2-wk preview + 10% contingency) | C23: ='Production Budget'!F261 -> 775408.21 | D23: =C23/'Production Budget'!F263 -> 0.1282122 | E23: Operating reserve and overrun protection
B24: TOTAL CAPITALIZATION | C24: =SUM(C15:C23) -> 6047850.3 | D24: 1
B26: CAPITALIZATION STRUCTURE (Recommended)
B27: Source | C27: Amount | D27: % | E27: Recoupment
B28: Investor Capital | C28: ='Production Budget'!F263*0.55 -> 3326317.7 | D28: 0.55 | E28: Recoupable: 120% + 50% profit share post-recoupment
B29: Institutional Grants (NEA, Mellon, LADF) | C29: ='Production Budget'!F263*0.25 -> 1511962.6 | D29: 0.25 | E29: Non-recoupable (mission-aligned)
B30: Individual Philanthropy / Major Gifts | C30: ='Production Budget'!F263*0.15 -> 907177.54 | D30: 0.15 | E30: Non-recoupable (named sponsorships)
B31: Community / Earned (memberships, crowdfunding) | C31: ='Production Budget'!F263*0.05 -> 302392.51 | D31: 0.05 | E31: Non-recoupable
B33: INVESTOR RETURN SCENARIOS
B34: Avg Capacity | C34: Weekly Contribution | D34: Weeks to Recoup | E34: Investor Recoup* | F34: Within 60-Wk Run?
B35: 100% | C35: =(('Seating Plan'!F26*1)+('Seating Plan'!G57*1))-(('Weekly Operating'!F124-0.03*'Seating Plan'!F26)+0.03*1*'Seating Plan'!F26) -> 44073 | D35: =IF((('Seating Plan'!F26*1)+('Seating Plan'!G57*1))-(('Weekly Operating'!F124-0.03*'Seating Plan'!F26)+0.03*1*'Seating Plan'!F26)>0,'Production Budget'!F263/((('Seating Plan'!F26*1)+('Seating Plan'!G57*1))-(('Weekly Operating'!F124-0.03*'Seating Plan'!F26)+0.03*1*'Seating Plan'!F26)),"—") -> 137.22348 | E35: =IF((('Seating Plan'!F26*1)+('Seating Plan'!G57*1))-(('Weekly Operating'!F124-0.03*'Seating Plan'!F26)+0.03*1*'Seating Plan'!F26)>0,('Production Budget'!F263)*0.55/((('Seating Plan'!F26*1)+('Seating Plan'!G57*1))-(('Weekly Operating'!F124-0.03*'Seating Plan'!F26)+0.03*1*'Seating Plan'!F26)),"—") -> 75.472912 | F35: =IF(AND((('Seating Plan'!F26*1)+('Seating Plan'!G57*1))-(('Weekly Operating'!F124-0.03*'Seating Plan'!F26)+0.03*1*'Seating Plan'!F26)>0,('Production Budget'!F263)*0.55/((('Seating Plan'!F26*1)+('Seating Plan'!G57*1))-(('Weekly Operating'!F124-0.03*'Seating Plan'!F26)+0.03*1*'Seating Plan'!F26))<=60),"YES","NO") -> NO
B36: 90% | C36: =(('Seating Plan'!F26*0.9)+('Seating Plan'!G57*0.9))-(('Weekly Operating'!F124-0.03*'Seating Plan'!F26)+0.03*0.9*'Seating Plan'!F26) -> 26579 | D36: =IF((('Seating Plan'!F26*0.9)+('Seating Plan'!G57*0.9))-(('Weekly Operating'!F124-0.03*'Seating Plan'!F26)+0.03*0.9*'Seating Plan'!F26)>0,'Production Budget'!F263/((('Seating Plan'!F26*0.9)+('Seating Plan'!G57*0.9))-(('Weekly Operating'!F124-0.03*'Seating Plan'!F26)+0.03*0.9*'Seating Plan'!F26)),"—") -> 227.54243 | E36: =IF((('Seating Plan'!F26*0.9)+('Seating Plan'!G57*0.9))-(('Weekly Operating'!F124-0.03*'Seating Plan'!F26)+0.03*0.9*'Seating Plan'!F26)>0,('Production Budget'!F263)*0.55/((('Seating Plan'!F26*0.9)+('Seating Plan'!G57*0.9))-(('Weekly Operating'!F124-0.03*'Seating Plan'!F26)+0.03*0.9*'Seating Plan'!F26)),"—") -> 125.14834 | F36: =IF(AND((('Seating Plan'!F26*0.9)+('Seating Plan'!G57*0.9))-(('Weekly Operating'!F124-0.03*'Seating Plan'!F26)+0.03*0.9*'Seating Plan'!F26)>0,('Production Budget'!F263)*0.55/((('Seating Plan'!F26*0.9)+('Seating Plan'!G57*0.9))-(('Weekly Operating'!F124-0.03*'Seating Plan'!F26)+0.03*0.9*'Seating Plan'!F26))<=60),"YES","NO") -> NO
B37: 85% | C37: =(('Seating Plan'!F26*0.85)+('Seating Plan'!G57*0.85))-(('Weekly Operating'!F124-0.03*'Seating Plan'!F26)+0.03*0.85*'Seating Plan'!F26) -> 17832 | D37: =IF((('Seating Plan'!F26*0.85)+('Seating Plan'!G57*0.85))-(('Weekly Operating'!F124-0.03*'Seating Plan'!F26)+0.03*0.85*'Seating Plan'!F26)>0,'Production Budget'!F263/((('Seating Plan'!F26*0.85)+('Seating Plan'!G57*0.85))-(('Weekly Operating'!F124-0.03*'Seating Plan'!F26)+0.03*0.85*'Seating Plan'!F26)),"—") -> 339.15715 | E37: =IF((('Seating Plan'!F26*0.85)+('Seating Plan'!G57*0.85))-(('Weekly Operating'!F124-0.03*'Seating Plan'!F26)+0.03*0.85*'Seating Plan'!F26)>0,('Production Budget'!F263)*0.55/((('Seating Plan'!F26*0.85)+('Seating Plan'!G57*0.85))-(('Weekly Operating'!F124-0.03*'Seating Plan'!F26)+0.03*0.85*'Seating Plan'!F26)),"—") -> 186.53643 | F37: =IF(AND((('Seating Plan'!F26*0.85)+('Seating Plan'!G57*0.85))-(('Weekly Operating'!F124-0.03*'Seating Plan'!F26)+0.03*0.85*'Seating Plan'!F26)>0,('Production Budget'!F263)*0.55/((('Seating Plan'!F26*0.85)+('Seating Plan'!G57*0.85))-(('Weekly Operating'!F124-0.03*'Seating Plan'!F26)+0.03*0.85*'Seating Plan'!F26))<=60),"YES","NO") -> NO
B38: 80% | C38: =(('Seating Plan'!F26*0.8)+('Seating Plan'!G57*0.8))-(('Weekly Operating'!F124-0.03*'Seating Plan'!F26)+0.03*0.8*'Seating Plan'!F26) -> 9085 | D38: =IF((('Seating Plan'!F26*0.8)+('Seating Plan'!G57*0.8))-(('Weekly Operating'!F124-0.03*'Seating Plan'!F26)+0.03*0.8*'Seating Plan'!F26)>0,'Production Budget'!F263/((('Seating Plan'!F26*0.8)+('Seating Plan'!G57*0.8))-(('Weekly Operating'!F124-0.03*'Seating Plan'!F26)+0.03*0.8*'Seating Plan'!F26)),"—") -> 665.69623 | E38: =IF((('Seating Plan'!F26*0.8)+('Seating Plan'!G57*0.8))-(('Weekly Operating'!F124-0.03*'Seating Plan'!F26)+0.03*0.8*'Seating Plan'!F26)>0,('Production Budget'!F263)*0.55/((('Seating Plan'!F26*0.8)+('Seating Plan'!G57*0.8))-(('Weekly Operating'!F124-0.03*'Seating Plan'!F26)+0.03*0.8*'Seating Plan'!F26)),"—") -> 366.13293 | F38: =IF(AND((('Seating Plan'!F26*0.8)+('Seating Plan'!G57*0.8))-(('Weekly Operating'!F124-0.03*'Seating Plan'!F26)+0.03*0.8*'Seating Plan'!F26)>0,('Production Budget'!F263)*0.55/((('Seating Plan'!F26*0.8)+('Seating Plan'!G57*0.8))-(('Weekly Operating'!F124-0.03*'Seating Plan'!F26)+0.03*0.8*'Seating Plan'!F26))<=60),"YES","NO") -> NO
B39: 75% | C39: =(('Seating Plan'!F26*0.75)+('Seating Plan'!G57*0.75))-(('Weekly Operating'!F124-0.03*'Seating Plan'!F26)+0.03*0.75*'Seating Plan'!F26) -> 338 | D39: =IF((('Seating Plan'!F26*0.75)+('Seating Plan'!G57*0.75))-(('Weekly Operating'!F124-0.03*'Seating Plan'!F26)+0.03*0.75*'Seating Plan'!F26)>0,'Production Budget'!F263/((('Seating Plan'!F26*0.75)+('Seating Plan'!G57*0.75))-(('Weekly Operating'!F124-0.03*'Seating Plan'!F26)+0.03*0.75*'Seating Plan'!F26)),"—") -> 17893.048 | E39: =IF((('Seating Plan'!F26*0.75)+('Seating Plan'!G57*0.75))-(('Weekly Operating'!F124-0.03*'Seating Plan'!F26)+0.03*0.75*'Seating Plan'!F26)>0,('Production Budget'!F263)*0.55/((('Seating Plan'!F26*0.75)+('Seating Plan'!G57*0.75))-(('Weekly Operating'!F124-0.03*'Seating Plan'!F26)+0.03*0.75*'Seating Plan'!F26)),"—") -> 9841.1765 | F39: =IF(AND((('Seating Plan'!F26*0.75)+('Seating Plan'!G57*0.75))-(('Weekly Operating'!F124-0.03*'Seating Plan'!F26)+0.03*0.75*'Seating Plan'!F26)>0,('Production Budget'!F263)*0.55/((('Seating Plan'!F26*0.75)+('Seating Plan'!G57*0.75))-(('Weekly Operating'!F124-0.03*'Seating Plan'!F26)+0.03*0.75*'Seating Plan'!F26))<=60),"YES","NO") -> NO
B40: 70% | C40: =(('Seating Plan'!F26*0.7)+('Seating Plan'!G57*0.7))-(('Weekly Operating'!F124-0.03*'Seating Plan'!F26)+0.03*0.7*'Seating Plan'!F26) -> -8409 | D40: =IF((('Seating Plan'!F26*0.7)+('Seating Plan'!G57*0.7))-(('Weekly Operating'!F124-0.03*'Seating Plan'!F26)+0.03*0.7*'Seating Plan'!F26)>0,'Production Budget'!F263/((('Seating Plan'!F26*0.7)+('Seating Plan'!G57*0.7))-(('Weekly Operating'!F124-0.03*'Seating Plan'!F26)+0.03*0.7*'Seating Plan'!F26)),"—") -> — | E40: =IF((('Seating Plan'!F26*0.7)+('Seating Plan'!G57*0.7))-(('Weekly Operating'!F124-0.03*'Seating Plan'!F26)+0.03*0.7*'Seating Plan'!F26)>0,('Production Budget'!F263)*0.55/((('Seating Plan'!F26*0.7)+('Seating Plan'!G57*0.7))-(('Weekly Operating'!F124-0.03*'Seating Plan'!F26)+0.03*0.7*'Seating Plan'!F26)),"—") -> — | F40: =IF(AND((('Seating Plan'!F26*0.7)+('Seating Plan'!G57*0.7))-(('Weekly Operating'!F124-0.03*'Seating Plan'!F26)+0.03*0.7*'Seating Plan'!F26)>0,('Production Budget'!F263)*0.55/((('Seating Plan'!F26*0.7)+('Seating Plan'!G57*0.7))-(('Weekly Operating'!F124-0.03*'Seating Plan'!F26)+0.03*0.7*'Seating Plan'!F26))<=60),"YES","NO") -> NO
B41: 65% | C41: =(('Seating Plan'!F26*0.65)+('Seating Plan'!G57*0.65))-(('Weekly Operating'!F124-0.03*'Seating Plan'!F26)+0.03*0.65*'Seating Plan'!F26) -> -17156 | D41: =IF((('Seating Plan'!F26*0.65)+('Seating Plan'!G57*0.65))-(('Weekly Operating'!F124-0.03*'Seating Plan'!F26)+0.03*0.65*'Seating Plan'!F26)>0,'Production Budget'!F263/((('Seating Plan'!F26*0.65)+('Seating Plan'!G57*0.65))-(('Weekly Operating'!F124-0.03*'Seating Plan'!F26)+0.03*0.65*'Seating Plan'!F26)),"—") -> — | E41: =IF((('Seating Plan'!F26*0.65)+('Seating Plan'!G57*0.65))-(('Weekly Operating'!F124-0.03*'Seating Plan'!F26)+0.03*0.65*'Seating Plan'!F26)>0,('Production Budget'!F263)*0.55/((('Seating Plan'!F26*0.65)+('Seating Plan'!G57*0.65))-(('Weekly Operating'!F124-0.03*'Seating Plan'!F26)+0.03*0.65*'Seating Plan'!F26)),"—") -> — | F41: =IF(AND((('Seating Plan'!F26*0.65)+('Seating Plan'!G57*0.65))-(('Weekly Operating'!F124-0.03*'Seating Plan'!F26)+0.03*0.65*'Seating Plan'!F26)>0,('Production Budget'!F263)*0.55/((('Seating Plan'!F26*0.65)+('Seating Plan'!G57*0.65))-(('Weekly Operating'!F124-0.03*'Seating Plan'!F26)+0.03*0.65*'Seating Plan'!F26))<=60),"YES","NO") -> NO
B43: *Investor Recoup column = weeks to recoup 55% investor tier only. Grants/philanthropy tiers are non-recoupable.

Sheet 3. Pitch Deck
B2: IF I AWAKEN IN LOS ANGELES
B3: Budget at a Glance
B5: CAPITALIZATION | D5: WEEKLY GROSS POTENTIAL
B6: ='Production Budget'!F263 -> 6047850.3 | D6: ='Seating Plan'!F26 -> 163000
B9: RUN LENGTH | D9: SHOWS PER WEEK
B10: "60 weeks" | D10: 12
B13: VENUE SIZE | D13: SEATS PER SHOW
B14: "30,100 sq ft" | D14: 150
B17: WHERE THE MONEY GOES
B18: Category | D18: Amount | E18: Share
B19: Build & Physical Production | D19: ='Production Budget'!F40+'Production Budget'!F210 -> 2505043.6 | E19: =D19/'Production Budget'!F263 -> 0.41420397
B20: People (Fees + Salaries) | D20: ='Production Budget'!F90+'Production Budget'!F135+'Production Budget'!F150+'Production Budget'!F166 -> 1508698.5 | E20: =D20/'Production Budget'!F263 -> 0.24946029
B21: Marketing & Launch | D21: ='Production Budget'!F187 -> 775500 | E21: =D21/'Production Budget'!F263 -> 0.12822738
B22: G&A, Bonds, Reserve | D22: ='Production Budget'!F225+'Production Budget'!F233+'Production Budget'!F252+'Production Budget'!F261 -> 1258608.2 | E22: =D22/'Production Budget'!F263 -> 0.20810836
B23: TOTAL | D23: =SUM(D19:D22) -> 6047850.3 | E23: 1
B25: ="Breakeven at "&TEXT(Recoupment!C28,"0.0%")&" capacity · Recoup investor tier in "&TEXT('Production Budget'!F263*0.55/(('Seating Plan'!F26*0.9+'Seating Plan'!G57*0.9)-(('Weekly Operating'!F124-0.03*'Seating Plan'!F26)+0.03*0.9*'Seating Plan'!F26)),"0")&" weeks at 90% avg capacity" -> Breakeven at 74.8% capacity · Recoup investor tier in 125 weeks at 90% avg capacity
B27: 60-week run · 12 shows/week · Tiered pricing with community access on every performance

Sheet Summary
A1: NOT FOR DISTRIBUTION
A2: Get Lit Collective / If I Awaken Productions
A3: Los Angeles, CA | info@ifiawaken.com
A4: CONFIDENTIAL | F4: as of: 4/20/26
A6: IF I AWAKEN IN LOS ANGELES
A7: IMMERSIVE THEATRE · LOS ANGELES · BUDGET SUMMARY · v2 (no royalties)
A9: PRODUCTION COSTS (CAPITALIZATION)
B10: (100) PHYSICAL | C10: ='Production Budget'!F40 -> 2314250
B11: (200) FIXED FEES | C11: ='Production Budget'!F90 -> 1008879
B12: (300) SALARIES (Pre-Opening) | C12: ='Production Budget'!F135 -> 394919.48
B13: (400) CASTING / REHEARSAL EXPENSES | C13: ='Production Budget'!F150 -> 53500
B14: (500) MUSIC EXPENSES | C14: ='Production Budget'!F166 -> 51400
B15: (600) ADVERTISING & PROMOTION | C15: ='Production Budget'!F187 -> 775500
B16: (700) VENUE & TECH (Load-In) | C16: ='Production Budget'!F210 -> 190793.6
B17: (800) GENERAL & ADMINISTRATIVE | C17: ='Production Budget'!F225 -> 174700
B18: (900) DEVELOPMENTAL | C18: ='Production Budget'!F233 -> 75000
B19: SUBTOTAL PRODUCTION COSTS: | C19: ='Production Budget'!F235 -> 5038942.1
B21: (950) BONDS, DEPOSITS, ADVANCES | C21: ='Production Budget'!F252 -> 233500
B22: (1000) CONTINGENCY & RESERVE | C22: ='Production Budget'!F261 -> 775408.21
B23: TOTAL CAPITALIZATION: | C23: ='Production Budget'!F263 -> 6047850.3
A26: WEEKLY OPERATING COSTS (NO ROYALTIES)
B27: (1100) PHYSICAL MAINTENANCE | C27: ='Weekly Operating'!F21 -> 9300
B28: (1200) FEES (WEEKLY) | C28: ='Weekly Operating'!F37 -> 8400
B29: (1300) SALARIES (incl. Director + Writer) | C29: ='Weekly Operating'!F84 -> 81007
B30: (1400) ADVERTISING | C30: ='Weekly Operating'!F97 -> 25500
B31: (1500) VENUE & TECH | C31: ='Weekly Operating'!F110 -> 8400
B32: (1600) GENERAL & ADMIN | C32: ='Weekly Operating'!F122 -> 3150
B33: TOTAL WEEKLY OPERATING: | C33: ='Weekly Operating'!F124 -> 135757
A36: WEEKLY GROSS POTENTIAL & KEY METRICS
B37: Weekly Gross Potential (100%): | C37: ='Seating Plan'!F26 -> 163000
B38: Weekly F&B / Merch Net Revenue: | C38: ='Seating Plan'!G57 -> 16830
B39: TOTAL WEEKLY REVENUE (100%): | C39: ='Seating Plan'!F26+'Seating Plan'!G57 -> 179830
B40: Weekly Contribution (100% cap): | C40: ='Seating Plan'!F26+'Seating Plan'!G57-'Weekly Operating'!F124 -> 44073
B41: Weekly Contribution (80% cap est.): | C41: =('Seating Plan'!F26*0.8+'Seating Plan'!G57*0.8)-(('Weekly Operating'!F124-0.03*'Seating Plan'!F26)+0.03*0.8*'Seating Plan'!F26) -> 9085
B43: Breakeven Capacity: | C43: =Recoupment!C28 -> 0.74806791
B44: Weeks to Recoup @ 80% Capacity: | C44: =IF(('Seating Plan'!F26*0.8+'Seating Plan'!G57*0.8)-(('Weekly Operating'!F124-0.03*'Seating Plan'!F26)+0.03*0.8*'Seating Plan'!F26)>0,'Production Budget'!F263/(('Seating Plan'!F26*0.8+'Seating Plan'!G57*0.8)-(('Weekly Operating'!F124-0.03*'Seating Plan'!F26)+0.03*0.8*'Seating Plan'!F26)),"—") -> 665.69623
A47: RECOMMENDED CAPITALIZATION STRUCTURE
B48: Source | C48: Amount | D48: % | E48: Notes
B49: Investor Capital (recoupable + profit share) | C49: =('Production Budget'!F263)*0.55 -> 3326317.7 | D49: 0.55 | E49: 120% recoupment + 50% profits post-recoup (despite no royalties, investors still get profit share).
B50: Institutional Grants (NEA, Mellon, LADF) | C50: =('Production Budget'!F263)*0.25 -> 1511962.6 | D50: 0.25 | E50: Mission-aligned arts funding — no recoupment obligation.
B51: Individual Philanthropy / Major Gifts | C51: =('Production Budget'!F263)*0.15 -> 907177.54 | D51: 0.15 | E51: Named sponsorships (spaces, programming) — no recoupment.
B52: Community / Earned (Kickstarter, memberships) | C52: =('Production Budget'!F263)*0.05 -> 302392.51 | D52: 0.05 | E52: Presale memberships + crowdfunding — community buy-in.
B53: TOTAL CAPITALIZATION: | C53: ='Production Budget'!F263 -> 6047850.3 | D53: 1
B55: Recoupable Portion (investor capital only):

Sheet Assumptions
A1: NOT FOR DISTRIBUTION
A2: Get Lit Collective / If I Awaken Productions
A3: Los Angeles, CA | info@ifiawaken.com
A4: CONFIDENTIAL | F4: as of: 4/20/26
A6: ASSUMPTIONS
B8: Rehearsal Weeks | C8: 2 | E8: AEA (Actors + SMs) | F8: SMs only
B9: Tech Weeks | C9: 2 | E9: SDC (Director/Choreographer) | F9: Y
B10: Preview Weeks | C10: 2 | E10: USA (Designers) | F10: Y
B11: Performance Weeks (run) | C11: 60 | E11: AFM Local 47 (Musicians) | F11: Y
B12: Shows per week | C12: 12 | E12: ATPAM (House/Press) | F12: N
B13: Seat Capacity per show | C13: 150 | E13: Contract Type | F13: AEA SM contract
B14: Venue Size (sq ft) | C14: 30100 | E14: Stage Manager (PSM) | F14: 1
B15: Monthly Warehouse Rent | C15: 20000 | E15: Assistant Stage Managers | F15: 2
B16: Performers — Poets/Actors | C16: 9 | E16: Production Assistants | F16: 2
B17: of which AEA | C17: 0 | E17: Board Ops / LED Tech | F17: 2
B18: of which non-union | C18: 9 | E18: Sound / A1 | F18: 1
B19: Performers — Dancers (non-union) | C19: 5 | E19: Wardrobe Supv + Dressers | F19: 3
B20: Performers — Musicians (AFM) | C20: 5 | E20: Props Crew | F20: 1
B21: Understudies / Swings | C21: 4 | E21: Royalty Structure | F21: None
B22: Tour Guides / Wranglers per show | C22: 1
B25: Project Notes:
B26: • Immersive theatre across six themed environments in a 30,100 sq ft LA warehouse (long-term lease, buildout by production).
B27: • Journey: Lobby (bar, gift shop, box office) + Space 1 LED intro -> Space 2 Boyle Heights -> Space 3 Asian
B28: neighborhoods -> Space 4 African-American neighborhoods -> Space 5 Canyons/folk -> Space 6 Concert -> Space 1 reprise.
B29: • Scenic concept: miniature LA — forced-perspective iconic buildings + full-scale street props (e.g., taco stand).
B30: • Premium lighting design: lighting is a primary storytelling device, steering audience focus across 6 environments.
B31: • Performers double as tour guides where narratively appropriate; 3 dedicated wranglers per show.
B32: • Music composed by Derrick Hodge (Grammy); production owns composition rights — no composer fee, no royalty.
B33: • Compressed schedule: 2 rehearsal + 2 tech + 2 preview weeks (6 weeks pre-opening).
B34: • Run: 60 performance weeks, 12 shows/week (Thu–Sun).
B35: • Director: Andrew Scoville (Theater of the Mind, Here Lies Love Assoc., Money Heist: The Experience NYC).
B36: • General Manager: Mark Chinapen. | Producer: Gina.
... B38: • Partial AEA: 6 of 15 poets/actors + all 3 SMs AEA; dancers and remaining 9 poets non-union; musicians AFM Local 47.

Sheet Production Budget
A1: NOT FOR DISTRIBUTION
A4: CONFIDENTIAL | F4: as of: 4/20/26
A6: PRODUCTION BUDGET — IMMERSIVE (150 CAP, 30,100 SQ FT WAREHOUSE)
A7: Cast: 15 Poets/Actors | 5 Dancers | 5 Musicians | 4 Understudies/Swings
A9: (100) PHYSICAL
C10: units | D10: rate | E10: amount | F10: subtotal
A11: (101) | B11: Scenery — Spaces 2/3/4/5 (neighborhood builds) | E11: 750000
A12: (101a) | B12: Scenery — Space 1 (LED lobby/intro) | E12: 35000
A13: (101b) | B13: Scenery — Space 6 (concert stage + seating) | E13: 125000
A14: (101c) | B14: Lobby Bar — Build, Equipment, POS, Inventory | E14: 45000
A15: (101d) | B15: Lobby Gift Shop — Fixtures, Display, POS, Initial Inventory | E15: 20000
A16: (101e) | B16: Lobby Box Office — Counter, Ticketing Hardware, Display | E16: 12000
A17: (102) | B17: Automation / Moving Scenic Elements | E17: 25000
A18: (103) | B18: Costumes — Performers (25 total cast) | C18: 25 | D18: 2000 | E18: =C18*D18 -> 50000
A19: (104) | B19: Understudy Costumes | C19: 4 | D19: 2000 | E19: =C19*D19 -> 8000
A20: (104a) | B20: Wardrobe Perishables | E20: 4500
A21: (105) | B21: Costume Maintenance (pre-show) | E21: 3000
A22: (106) | B22: Electrics Purchase (premium install — 6 spaces) | E22: 200000
A23: (107) | B23: Electrics Rental (Tech) | E23: 22000
A24: (108) | B24: Sound Purchase (install — 6 spaces) | E24: 65000
A25: (109) | B25: Sound Rental (Tech) | E25: 15000
A26: (110) | B26: Props / Furniture (6 spaces) | E26: 140000
A27: (111) | B27: Special Effects (haze, fog, atmospherics) | E27: 15000
A28: (112) | B28: Projections Equipment (non-LED) | E28: 30000
A29: (113) | B29: LED Wall — Purchase (110 ft x 14 ft) | E29: 385000
A30: (113a) | B30: LED Media Servers / Playback Infrastructure | E30: 55000
A31: (113b) | B31: LED Content Creation / Video Production | E31: 75000
A32: (114) | B32: Hair / Wigs / Makeup | E32: 12000
A33: (115) | B33: Designer Expenses | C33: 9 | D33: 750 | E33: =C33*D33 -> 6750
A34: (116) | B34: Departmental Expenses / Hardware | E34: 8000
A35: (117) | B35: Carting / Trucking / Storage | E35: 18000
A36: (118) | B36: Venue Permitting & Occupancy Buildout | E36: 30000
A37: (119) | B37: Security Infrastructure (cameras, access, install, training) | E37: 85000
A38: (120) | B38: Exterior Wall Paint/Mural Wrap (front — ~3,820 sq ft) | E38: 75000
B40: TOTAL 100 — PHYSICAL | F40: =SUM(E11:E38) -> 2314250
A42: (200) FIXED FEES
C43: units | D43: rate | E43: amount | F43: subtotal
A44: (201) | B44: Author / Book Writer (includes 50% of run-period salary) | E44: 110000
A45: (203) | B45: Director — Andrew Scoville (includes 50% of run-period salary) | E45: 125000
A46: (204) | B46: Assistant Director | E46: 12000
A47: (205) | B47: Choreographer | E47: 20000
A48: (206) | B48: Assistant Choreographer | E48: 8000
A49: (207) | B49: Scenic Designer (6 environments) | E49: 28000
A50: (208) | B50: Assistant Scenic Designer | E50: 9000
A51: (209) | B51: Costume Designer | E51: 18000
A52: (210) | B52: Assistant Costume Designer | E52: 6000
A53: (211) | B53: Lighting Designer (premium — lead design across 6 spaces) | E53: 45000
A54: (211a) | B54: Associate Lighting Designer | E54: 22000
A55: (212) | B55: Assistant Lighting Designer | E55: 12000
... A82: (237) | B82: Marketing / Social Media Startup | E82: 10000
A83: (238) | B83: SDC Pension 4.5% (on Director + Chor fees) | D83: 0.045 | E83: =D83*(E45+E46+E47+E48) -> 7425
A84: (239) | B84: SDC Health (4 positions × 8 wks × $187) | C84: 32 | D84: 187 | E84: =C84*D84 -> 5984
A85: (240) | B85: USA Health 13% (on designer fees) | D85: 0.13 | E85: =D85*SUM(E49:E59) -> 26260
A86: (241) | B86: USA Pension 9% (on designer fees) | D86: 0.09 | E86: =D86*SUM(E49:E59) -> 18180
A87: (242) | B87: USA Benefits 25% (on designer fees) | D87: 0.25 | E87: =D87*SUM(E49:E59) -> 50500
A88: (243) | B88: Payroll Taxes 18% (on W-2 creative fees) | D88: 0.18 | E88: =D88*SUM(E45:E71) -> 78030
B90: TOTAL 200 — FIXED FEES | F90: =SUM(E44:E88) -> 1008879
A92: (300) SALARIES — REHEARSAL / TECH / PREVIEW (2+2+2 wks)
C93: units | D93: rate | E93: amount | F93: subtotal
A94: (301) | B94: Stars | C94: 0 | D94: 0 | E94: =C94*D94 -> 0
A95: (302) | B95: Principals — AEA (6 × 4 wks) | C95: 24 | D95: 1600 | E95: =C95*D95 -> 38400
A96: (302a) | B96: Principals — Non-union Poets (9 × 4 wks) | C96: 36 | D96: 1400 | E96: =C96*D96 -> 50400
A97: (302b) | B97: Dancers — Non-union (5 × 4 wks) | C97: 20 | D97: 1300 | E97: =C97*D97 -> 26000
A98: (303) | B98: Dance Captain premium (4 wks × 18%) | C98: 4 | D98: 234 | E98: =C98*D98 -> 936
A99: (304) | B99: Swings / Understudies (4 × 4 wks) | C99: 16 | D99: 1400 | E99: =C99*D99 -> 22400
A100: (305) | B100: Stage Manager (PSM, AEA) — 4 wks | C100: 4 | D100: 1900 | E100: =C100*D100 -> 7600
A101: (305.5) | B101: PSM Pre-Production Prep | C101: 1 | D101: 1900 | E101: =C101*D101 -> 1900
A102: (305.6) | B102: PSM Tech Bump (2 wks × 33%) | C102: 2 | D102: 630 | E102: =C102*D102 -> 1260
A103: (306) | B103: Assistant Stage Managers (AEA, 2 × 4 wks) | C103: 8 | D103: 1750 | E103: =C103*D103 -> 14000
A104: (306.6) | B104: ASM Tech Bumps (2 × 2 wks × 33%) | C104: 4 | D104: 580 | E104: =C104*D104 -> 2320
A105: (306.8) | B105: ASM Previews (2 × 2 wks) | C105: 4 | D105: 1750 | E105: =C105*D105 -> 7000
... A110: (308c) | B110: Musicians Hourly Rehearsal Calls | C110: 20 | D110: 95 | E110: =C110*D110 -> 1900
A111: (309) | B111: Musician Contractor Fee | E111: 3000
A112: (311) | B112: Musicians — Synth Programmer | E112: 4500
A113: (312) | B113: Audition / Rehearsal Pianist | E113: 4000
A114: (313) | B114: Lighting Board Op (tech/preview hrs) | C114: 60 | D114: 45 | E114: =C114*D114 -> 2700
A115: (314) | B115: Lighting Programmer (premium — 6 spaces) | C115: 120 | D115: 75 | E115: =C115*D115 -> 9000
A116: (315) | B116: LED Wall / Media Server Programmer | C116: 60 | D116: 85 | E116: =C116*D116 -> 5100
A117: (317) | B117: Sound Crew / A1 (tech+preview) | C117: 4 | D117: 1400 | E117: =C117*D117 -> 5600
A118: (319) | B118: Props Crew (tech+preview) | C118: 4 | D118: 1000 | E118: =C118*D118 -> 4000
A119: (320) | B119: Wardrobe Supervisor (tech+preview) | C119: 4 | D119: 1100 | E119: =C119*D119 -> 4400
A120: (321) | B120: Dressers (2 × 4 wks) | C120: 8 | D120: 900 | E120: =C120*D120 -> 7200
A121: (322) | B121: Audio Engineer (Head A2) | C121: 4 | D121: 1200 | E121: =C121*D121 -> 4800
A122: (323) | B122: General Manager (weekly retainer, 6 wks pre-open) | C122: 6 | D122: 2500 | E122: =C122*D122 -> 15000
A123: (324) | B123: Company / House Manager (6 wks pre-open) | C123: 6 | D123: 1400 | E123: =C123*D123 -> 8400
A124: (325) | B124: Tour Guide / Wrangler Training (3 × 2 wks) | C124: 6 | D124: 900 | E124: =C124*D124 -> 5400
A125: (326) | B125: AEA Overtime Contingency | E125: 5000
A126: (327) | B126: AFM Overtime Contingency | E126: 3000
A127: (328) | B127: Crew Overtime Contingency | E127: 5000
A128: (329) | B128: AEA SM Health (3 SMs × 5 wks × $190) | C128: 15 | D128: 190 | E128: =C128*D128 -> 2850
A129: (331) | B129: AEA Actor Health (8 AEA × 4 wks × $190) | C129: 32 | D129: 190 | E129: =C129*D129 -> 6080
A130: (332) | B130: AEA Pension 8% (on AEA salaries) | D130: 0.08 | E130: =D130*(E95+E99+E100+E101+E102+E103+E104+E105) -> 7590.4
A131: (333) | B131: AEA New Media 1.5% (on AEA salaries) | D131: 0.015 | E131: =D131*(E95+E99+E100+E101+E102+E103+E104+E105) -> 1423.2
A132: (333a) | B132: AFM Pension + H&W ~15% (on musicians) | D132: 0.15 | E132: =D132*(E109+E110) -> 3585
A133: (334) | B133: Payroll Taxes 18% (on W-2 salaries) | D133: 0.18 | E133: =D133*SUM(E95:E124) -> 54974.88
B135: TOTAL 300 — SALARIES | F135: =SUM(E94:E133) -> 394919.48
A137: (400) CASTING / REHEARSAL EXPENSES
C138: units | D138: rate | E138: amount | F138: subtotal
A139: (401) | B139: Audition Space Rental (40 sessions × $125) | C139: 40 | D139: 125 | E139: =C139*D139 -> 5000
A140: (402) | B140: Rehearsal Space Rental (LA — 2 wks) | C140: 2 | D140: 4500 | E140: =C140*D140 -> 9000
...

Sheet Weekly Operating
A1: NOT FOR DISTRIBUTION
A2: CONFIDENTIAL | F2: as of: 4/20/26
A4: WEEKLY OPERATING BUDGET
A5: Per-week costs during 60-week run — NO ROYALTIES model (Director + Writer on salary)
A7: (1100) PHYSICAL MAINTENANCE
C8: units | D8: rate | E8: amount | F8: subtotal
A9: (1101) | B9: Costume Maintenance / Replacements | E9: 800
A10: (1102) | B10: Hair / Makeup Supplies | E10: 500
A11: (1103) | B11: Prop Replacements / Perishables | E11: 600
A12: (1104) | B12: Electrics Maintenance (premium lighting, 6 spaces) | E12: 800
A13: (1105) | B13: LED Wall Service Contract / Parts | E13: 1500
A14: (1106) | B14: Sound Maintenance / Batteries / Parts | E14: 400
A15: (1107) | B15: Scenic Repair / Paint / Hardware | E15: 600
A16: (1108) | B16: Cleaning / Janitorial (30K sqft) | E16: 2500
A17: (1109) | B17: Sanitation / Restroom Supplies | E17: 300
A18: (1110) | B18: Load-Out Accrual (weekly) | E18: 500
A19: (1111) | B19: Bar / Gift Shop — Restocking Allowance | E19: 800
B21: TOTAL 1100 — PHYSICAL MAINTENANCE | F21: =SUM(E9:E19) -> 9300
A23: (1200) FEES (WEEKLY)
C24: units | D24: rate | E24: amount | F24: subtotal
A25: (1201) | B25: General Management (50% — other 50% in prod budget) | E25: 1250
A26: (1202) | B26: Production Supervisor / Resident Director — ELIMINATED | E26: 0
A27: (1203) | B27: Music Director (weekly) — CUT | E27: 0
A28: (1204) | B28: Press Agent (weekly) | E28: 2000
A29: (1205) | B29: Advertising Agency (weekly) | E29: 1500
A30: (1206) | B30: Marketing / Social Media Agency | E30: 1500
A31: (1207) | B31: Casting Director (ongoing) — CUT | E31: 0
A32: (1208) | B32: Accounting / Bookkeeping (weekly) | E32: 1000
A33: (1209) | B33: Legal Retainer | E33: 400
A34: (1210) | B34: Payroll Service | E34: 250
A35: (1211) | B35: Property Manager (weekly) | E35: 500
B37: TOTAL 1200 — FEES | F37: =SUM(E25:E35) -> 8400
A39: (1300) SALARIES (WEEKLY)
C40: units | D40: rate | E40: amount | F40: subtotal
A41: (1300a) | B41: Producer - Diane Lane | C41: 1 | D41: 6730 | E41: =C41*D41 -> 6730
A42: (1300a) | B42: Producer - Brandon Jordan | C42: 1 | D42: 4807 | E42: =C42*D42 -> 4807
A43: (1300a) | B43: Producer - Gina Belafonte | C43: 1 | D43: 961 | E43: =C43*D43 -> 961
A44: (1300a) | B44: Director - Scoville (50% — other 50% in prod budget) | C44: 1 | D44: 1250 | E44: =C44*D44 -> 1250
A45: (1300b) | B45: Writer - Monique (50% — other 50% in prod budget) | C45: 1 | D45: 2885 | E45: =C45*D45 -> 2885
A46: (1301) | B46: Principals — AEA — ELIMINATED (cast now all non-union) | C46: 0 | D46: 1600 | E46: =C46*D46 -> 0
A47: (1301a) | B47: Principals — Non-union Poets (6) | C47: 6 | D47: 1400 | E47: =C47*D47 -> 8400
A48: (1301b) | B48: Dancers — Non-union (5) | C48: 5 | D48: 1300 | E48: =C48*D48 -> 6500
A49: (1301c) | B49: Tour Guide Actors (non-union, 2 — in-cast guides) | C49: 2 | D49: 1400 | E49: =C49*D49 -> 2800
A50: (1301d) | B50: Teenage Singer (minor, non-union) — OPTIONAL | C50: 1 | D50: 1400 | E50: =C50*D50 -> 1400
A51: (1301e) | B51: Studio Teacher (required when minor is on-site) — OPTIONAL | C51: 12 | D51: 60 | E51: =C51*D51 -> 720
A52: (1302) | B52: Dance Captain premium (18%) | C52: 1 | D52: 234 | E52: =C49*D49 -> 2800
A53: (1303) | B53: Musicians — AFM (5) | C53: 5 | D53: 1100 | E53: =C50*D50 -> 1400
A54: (1304) | B54: Musician Contractor Premium | C54: 1 | D54: 200 | E54: =C51*D51 -> 720
A55: (1305) | B55: Swings / Understudies (4) | C55: 4 | D55: 1400 | E55: =C52*D52 -> 234
A56: (1306) | B56: Stage Manager (PSM, AEA) | C56: 1 | D56: 1900 | E56: =C53*D53 -> 5500
A57: (1307) | B57: Assistant Stage Managers (AEA, 2) | C57: 2 | D57: 1750 | E57: =C54*D54 -> 200
A58: (1308) | B58: Production Assistants (2) | C58: 2 | D58: 800 | E58: =C55*D55 -> 5600
A59: (1309) | B59: Company / House Manager | C59: 1 | D59: 1400 | E59: =C56*D56 -> 1900
A60: (1310) | B60: LED Wall / Media Server Tech | C60: 1 | D60: 1500 | E60: =C57*D57 -> 3500
A61: (1311) | B61: Lighting Board Op (premium design) | C61: 1 | D61: 1500 | E61: =C58*D58 -> 1600
A62: (1311a) | B62: Associate Lighting Designer (running — weekly) | C62: 1 | D62: 1200 | E62: =C59*D59 -> 1400
A63: (1312) | B63: Sound A1 | C63: 1 | D63: 1400 | E63: =C60*D60 -> 1500
... A69: (1318) | B69: Audience Shepherd (1 per show × 12 shows × $225 — with radio) | C69: 12 | D69: 225 | E69: =C66*D66 -> 1800
A70: (1319) | B70: Front of House Staff / Ushers | E70: 2500
A71: (1320) | B71: Box Office / Ticketing Staff | E71: 1500
A72: (1320a) | B72: Bar Staff (2-3 on shift) | E72: 1800
A73: (1320b) | B73: Gift Shop Staff (1-2 on shift) | E73: 900
A74: (1321) | B74: Security (ongoing — event staff) | E74: 2000
A75: (1322) | B75: AEA Overtime Reserve | E75: 800
A76: (1323) | B76: Crew Overtime Reserve | E76: 600
A77: (1324) | B77: AEA Health (3 SMs × $190/wk) | C77: 3 | D77: 190 | E77: =C74*D74 -> 0
A78: (1325) | B78: AEA Pension 8% (on AEA SM salaries only) | D78: 0.08 | E78: =D78*(E56+E57) -> 456
A79: (1326) | B79: AEA New Media 1.5% (on AEA SM salaries only) | D79: 0.015 | E79: =D79*(E56+E57) -> 85.5
A80: (1327) | B80: AFM Pension + H&W ~15% (on musicians) | D80: 0.15 | E80: =D77*(E50+E51) -> 402800
A81: (1327a) | B81: SDC Weekly Benefits (Director salary: pension+health) | D81: 0.13 | E81: =D78*E44 -> 100
A82: (1328) | B82: Payroll Taxes 18% (on W-2 weekly salaries) | D82: 0.18 | E82: =D79*SUM(E44:E73) -> 976.635
B84: TOTAL 1300 — SALARIES | F84: =SUM(E41:E76) -> 81007
A86: (1400) ADVERTISING (WEEKLY)
C87: units | D87: rate | E87: amount | F87: subtotal
A88: (1401) | B88: Digital / Social Media Ad Spend | E88: 5000
A89: (1402) | B89: OOH / Transit / Billboard | E89: 2000
A90: (1403) | B90: Print / Newspaper / Magazine | E90: 1500
A91: (1404) | B91: Radio / Podcast | E91: 1200
A92: (1405) | B92: Photography / Video Refresh | E92: 5000
A93: (1406) | B93: Programs & Printing | E93: 5000
A94: (1407) | B94: Press Events / Openings | E94: 5000
A95: (1408) | B95: Group Sales Commissions | E95: 800
B97: TOTAL 1400 — ADVERTISING | F97: =SUM(E88:E95) -> 25500
A99: (1500) VENUE & TECH (WEEKLY)
C100: units | D100: rate | E100: amount | F100: subtotal
A101: (1501) | B101: Warehouse Rent ($20K/mo ÷ 4) | E101: 5000
A102: (1502) | B102: Utilities — Electricity (HVAC for large warehouse) | E102: 1800
A103: (1503) | B103: Utilities — Water / Gas / Trash | E103: 300
A104: (1504) | B104: Internet / Phone / Tech Infrastructure | E104: 200
A105: (1505) | B105: Equipment Rental Continuing | E105: 400
A106: (1506) | B106: Expendables (gel, gaff, batteries, consumables) | E106: 500
A107: (1507) | B107: Pest Control / Maintenance Service | E107: 200
A108: (1508) | B108: Credit Card / Ticketing Processing (3% GWBOR) | D108: 0.03 | E108: =D105*'Seating Plan'!F26 -> 0
B110: TOTAL 1500 — VENUE & TECH | F110: =SUM(E101:E108) -> 8400
A112: (1600) GENERAL & ADMINISTRATIVE (WEEKLY)
C113: units | D113: rate | E113: amount | F113: subtotal
A114: (1601) | B114: Insurance Accrual (GL, participant, WC) | E114: 1500
A115: (1602) | B115: Office / Supplies | E115: 300
A116: (1603) | B116: Travel & Housing (continuing) | E116: 500
A117: (1604) | B117: Per Diem (out-of-town creatives) | E117: 400
...

Sheet Seating Plan
A1: NOT FOR DISTRIBUTION
A2: CONFIDENTIAL | F2: as of: 4/20/26
A4: SEATING PLAN & GROSS POTENTIAL — TIERED WITHIN-SHOW PRICING
A5: 150-cap immersive · 12 shows/week · Every show has Community pricing
B7: Capacity per Show: | C7: 150
B8: Shows per Week: | C8: 12
B9: Weekly Capacity (seats): | C9: =C7*C8 -> 1800
A11: Day | B11: Tier | C11: Shows/Wk | D11: Seats/Show | E11: Price | F11: Weekly Gross
A12: Thursday — COMMUNITY NIGHT | B12: Community | C12: 2 | D12: 80 | E12: 40 | F12: =C12*D12*E12 -> 6400
B13: Standard | C13: 2 | D13: 50 | E13: 60 | F13: =C13*D13*E13 -> 6000
B14: Premium | C14: 2 | D14: 20 | E14: 80 | F14: =C14*D14*E14 -> 3200
A15: Friday | B15: Community | C15: 2 | D15: 40 | E15: 50 | F15: =C15*D15*E15 -> 4000
B16: Standard | C16: 2 | D16: 70 | E16: 80 | F16: =C16*D16*E16 -> 11200
B17: Premium | C17: 2 | D17: 40 | E17: 110 | F17: =C17*D17*E17 -> 8800
A18: Saturday — PEAK | B18: Community | C18: 4 | D18: 30 | E18: 60 | F18: =C18*D18*E18 -> 7200
B19: Standard | C19: 4 | D19: 50 | E19: 100 | F19: =C19*D19*E19 -> 20000
B20: Premium | C20: 4 | D20: 50 | E20: 140 | F20: =C20*D20*E20 -> 28000
B21: VIP (bar + shop voucher) | C21: 4 | D21: 20 | E21: 185 | F21: =C21*D21*E21 -> 14800
A22: Sunday | B22: Community | C22: 4 | D22: 40 | E22: 55 | F22: =C22*D22*E22 -> 8800
B23: Standard | C23: 4 | D23: 60 | E23: 90 | F23: =C23*D23*E23 -> 21600
B24: Premium | C24: 4 | D24: 50 | E24: 115 | F24: =C24*D24*E24 -> 23000
B26: WEEKLY GROSS POTENTIAL (100%): | F26: =SUM(F12:F24) -> 163000
B27: Weighted Average Ticket Price: | F27: =F26/C9 -> 90.555556
B29: Weekly Community Seats (accessible tier): | F29: =C12*D12+C15*D15+C18*D18+C22*D22 -> 520
B31: Capacity Scenarios:
B32: Capacity % | C32: Weekly Gross | D32: Tickets/Wk | E32: Avg Price
B33: 110% | C33: =F26*1.1 -> 179300 | D33: =C7*C8*1.1 -> 1980 | E33: =C33/D33 -> 90.555556
B34: 100% | C34: =F26*1 -> 163000 | D34: =C7*C8*1 -> 1800 | E34: =C34/D34 -> 90.555556
B35: 90% | C35: =F26*0.9 -> 146700 | D35: =C7*C8*0.9 -> 1620 | E35: =C35/D35 -> 90.555556
B36: 80% | C36: =F26*0.8 -> 130400 | D36: =C7*C8*0.8 -> 1440 | E36: =C36/D36 -> 90.555556
B37: 70% | C37: =F26*0.7 -> 114100 | D37: =C7*C8*0.7 -> 1260 | E37: =C37/D37 -> 90.555556
B38: 60% | C38: =F26*0.6 -> 97800 | D38: =C7*C8*0.6 -> 1080 | E38: =C38/D38 -> 90.555556
B39: 50% | C39: =F26*0.5 -> 81500 | D39: =C7*C8*0.5 -> 900 | E39: =C39/D39 -> 90.555556
B41: Pricing Philosophy:
B42: • Within-show tiered pricing: every performance has Community seats — accessibility is built into every show, not isolated to one night.
B43: • Community tier ($40-60) = accessible for students, LA neighborhood partners, Get Lit alumni, nonprofit coalitions.
B44: • Standard tier = market-rate ticket for general audience.
B45: • Premium tier = committed theatergoers / tourists / immersive enthusiasts.
B46: • VIP tier (Saturday only, 20 seats/show) = bar credit + gift shop voucher + priority entry. Effectively subsidizes Community tier.
B47: • Weighted avg ~$91/ticket (vs. $99 in v2) — meaningful reduction via access tier on every performance.
B48: • Thursday Community Night reserves 80 of 150 seats at $40 — the deepest access slot in the week.
B49: • 110% capacity scenario = bar, gift shop, merch, concessions, group add-ons. Real upside not modeled in GWBOR.
A52: F&B / MERCHANDISE REVENUE (per-cap model)
B53: Category | C53: Per-Cap | D53: Penetration | E53: Weekly Gross | F53: COGS % | G53: Weekly Net
B54: Bar / Cocktails | C54: 12 | D54: 0.7 | E54: =C54*C9*D54 -> 15120 | F54: 0.25 | G54: =E54*(1-F54) -> 11340
B55: Food / Concessions | C55: 6 | D55: 0.5 | E55: =C55*C9*D55 -> 5400 | F55: 0.35 | G55: =E55*(1-F55) -> 3510
B56: Merchandise (programs, tees, vinyl) | C56: 8 | D56: 0.25 | E56: =C56*C9*D56 -> 3600 | F56: 0.45 | G56: =E56*(1-F56) -> 1980
B57: TOTAL F&B / MERCH: | E57: =SUM(E54:E56) -> 24120 | G57: =SUM(G54:G56) -> 16830
B59: COMBINED WEEKLY REVENUE (Tickets + F&B Net): | G59: =F26+G57 -> 179830

Sheet Recoupment
A1: NOT FOR DISTRIBUTION
A4: CONFIDENTIAL | F4: as of: 4/20/26
A6: RECOUPMENT SCHEDULE
A7: Weeks to recoup capitalization — no-royalty model
B9: Total Capitalization: | C9: ='Production Budget'!F263 -> 6047850.3
B10: Weekly Operating Cost (at 100% GWBOR): | C10: ='Weekly Operating'!F124 -> 135757
B11: Weekly Gross Potential (100%): | C11: ='Seating Plan'!F26 -> 163000
B13: Capacity % | C13: Weekly GWBOR | D13: Weekly Op Cost | E13: Total Contrib. (Tix+F&B−Op) | F13: Weeks to Recoup | G13: Months to Recoup
B14: 110% | C14: =C11*1.1 -> 179300 | D14: =(C10-0.03*C11)+0.03*C14 -> 136246 | E14: =C14+('Seating Plan'!G57*1.1)-D14 -> 61567 | F14: =IF(E14>0,C9/E14,"—") -> 98.232012 | G14: =IF(E14>0,F14/4.33,"—") -> 22.686377
B15: 100% | C15: =C11*1 -> 163000 | D15: =(C10-0.03*C11)+0.03*C15 -> 135757 | E15: =C15+('Seating Plan'!G57*1)-D15 -> 44073 | F15: =IF(E15>0,C9/E15,"—") -> 137.22348 | G15: =IF(E15>0,F15/4.33,"—") -> 31.691334
B16: 95% | C16: =C11*0.95 -> 154850 | D16: =(C10-0.03*C11)+0.03*C16 -> 135512.5 | E16: =C16+('Seating Plan'!G57*0.95)-D16 -> 35326 | F16: =IF(E16>0,C9/E16,"—") -> 171.20111 | G16: =IF(E16>0,F16/4.33,"—") -> 39.538362
B17: 90% | C17: =C11*0.9 -> 146700 | D17: =(C10-0.03*C11)+0.03*C17 -> 135268 | E17: =C17+('Seating Plan'!G57*0.9)-D17 -> 26579 | F17: =IF(E17>0,C9/E17,"—") -> 227.54243 | G17: =IF(E17>0,F17/4.33,"—") -> 52.550215
B18: 85% | C18: =C11*0.85 -> 138550 | D18: =(C10-0.03*C11)+0.03*C18 -> 135023.5 | E18: =C18+('Seating Plan'!G57*0.85)-D18 -> 17832 | F18: =IF(E18>0,C9/E18,"—") -> 339.15715 | G18: =IF(E18>0,F18/4.33,"—") -> 78.327286
B19: 80% | C19: =C11*0.8 -> 130400 | D19: =(C10-0.03*C11)+0.03*C19 -> 134779 | E19: =C19+('Seating Plan'!G57*0.8)-D19 -> 9085 | F19: =IF(E19>0,C9/E19,"—") -> 665.69623 | G19: =IF(E19>0,F19/4.33,"—") -> 153.74047
B20: 75% | C20: =C11*0.75 -> 122250 | D20: =(C10-0.03*C11)+0.03*C20 -> 134534.5 | E20: =C20+('Seating Plan'!G57*0.75)-D20 -> 338 | F20: =IF(E20>0,C9/E20,"—") -> 17893.048 | G20: =IF(E20>0,F20/4.33,"—") -> 4132.3437
B21: 70% | C21: =C11*0.7 -> 114100 | D21: =(C10-0.03*C11)+0.03*C21 -> 134290 | E21: =C21+('Seating Plan'!G57*0.7)-D21 -> -8409 | F21: =IF(E21>0,C9/E21,"—") -> — | G21: =IF(E21>0,F21/4.33,"—") -> —
B22: 65% | C22: =C11*0.65 -> 105950 | D22: =(C10-0.03*C11)+0.03*C22 -> 134045.5 | E22: =C22+('Seating Plan'!G57*0.65)-D22 -> -17156 | F22: =IF(E22>0,C9/E22,"—") -> — | G22: =IF(E22>0,F22/4.33,"—") -> —
B23: 60% | C23: =C11*0.6 -> 97800 | D23: =(C10-0.03*C11)+0.03*C23 -> 133801 | E23: =C23+('Seating Plan'!G57*0.6)-D23 -> -25903 | F23: =IF(E23>0,C9/E23,"—") -> — | G23: =IF(E23>0,F23/4.33,"—") -> —
B24: 55% | C24: =C11*0.55 -> 89650 | D24: =(C10-0.03*C11)+0.03*C24 -> 133556.5 | E24: =C24+('Seating Plan'!G57*0.55)-D24 -> -34650 | F24: =IF(E24>0,C9/E24,"—") -> — | G24: =IF(E24>0,F24/4.33,"—") -> —
B25: 50% | C25: =C11*0.5 -> 81500 | D25: =(C10-0.03*C11)+0.03*C25 -> 133312 | E25: =C25+('Seating Plan'!G57*0.5)-D25 -> -43397 | F25: =IF(E25>0,C9/E25,"—") -> — | G25: =IF(E25>0,F25/4.33,"—") -> —
B26: 45% | C26: =C11*0.45 -> 73350 | D26: =(C10-0.03*C11)+0.03*C26 -> 133067.5 | E26: =C26+('Seating Plan'!G57*0.45)-D26 -> -52144 | F26: =IF(E26>0,C9/E26,"—") -> — | G26: =IF(E26>0,F26/4.33,"—") -> —
B28: BREAKEVEN CAPACITY: | C28: =('Weekly Operating'!F124-0.03*'Seating Plan'!F26)/(0.97*'Seating Plan'!F26+'Seating Plan'!G57) -> 0.74806791
B29: Breakeven Weekly GWBOR: | C29: =C28*C11 -> 121935.07
B30: Breakeven Avg Tickets / Show: | C30: =C28*150 -> 112.21019
B32: Notes:
B33: • REVISED: Weekly contribution now includes F&B/Merch net revenue ($XX/wk at 100%) — see Seating Plan.
B34: • Only ~3% of weekly op varies with capacity (CC fees). No royalties means far more fixed overhead.
B35: • NO ROYALTY model means breakeven is determined almost entirely by fixed weekly operating costs.
B36: • Show scheduled for 60-week run; any scenario requiring >60 weeks does not recoup within the run.
B37: • Does NOT include bar, gift shop, concessions revenue — these are real upside with expanded lobby.
B38: • Bar + gift shop could add 15-25% to gross revenue — conservative models add $15-30K/wk.
B39: • Without royalties, creative team has zero upside participation — may limit future revivals/licensing.

Sheet Events Upside
A1: NOT FOR DISTRIBUTION
A4: CONFIDENTIAL | F4: as of: 4/27/26
A6: EVENTS / SECOND BUSINESS — UPSIDE SCENARIO
A7: Venue rentals on dark days (Mon–Wed + weekday daytime). NOT included in main budget recoupment math.
A9: OPPORTUNITY CONTEXT
B10: The show occupies the venue Thu–Sun evenings + weekend afternoons. Mon–Wed and weekday daytime sit dark.
B11: That's ~3.5 fully rentable days/week × 60 weeks = ~210 day-equivalents of unused premium real estate.
A13: VENUE ASSETS (LA Market Rates)
B14: Asset | C14: Low ($/day) | D14: High ($/day) | E14: Notes
B15: 110-ft permanent LED wall | C15: 5000 | D15: 20000 | E15: LA's most dramatic indoor screen
B16: Real bar program | C16: 8000 | D16: 15000 | E16: 64-ft bar, neon, leather booths, VIP zone
B17: 150-seat proscenium theater | C17: 5000 | D17: 10000 | E17: With stage
B18: Outdoor red-carpet courtyard | C18: 3000 | D18: 10000 | E18: With marquee — premiere-tier, rare in LA
B19: 30,000 sq ft of versatile space | C19: 10000 | D19: 18000 | E19: 500+ guest cocktail capacity
B20: Arts District location | C20: — | D20: — | E20: Premium real estate; included in above
A22: WHAT WE SELL
B23: Offering | C23: Low Rate | D23: High Rate | E23: Use Case
B24: Full venue buyout | C24: 25000 | D24: 45000 | E24: Premieres, brand activations, wrap parties
B25: Single-space rental | C25: 6000 | D25: 12000 | E25: All-hands, product launches, dinners
B26: Production / filming day rate | C26: 8000 | D26: 18000 | E26: Music videos, commercials, photo shoots
B27: Recurring programs | C27: 2000 | D27: 5000 | E27: Comedy nights, podcast tapings, salons
A29: RUN-PERIOD REVENUE SCENARIOS (60 weeks)
B30: Scenario | C30: Utilization | D30: Avg Day Rate | E30: Run Gross | F30: Direct Costs | G30: Run Net
B31: Conservative | C31: 0.3 | D31: 8500 | E31: =210*C31*D31 -> 535500 | F31: =E31*0.25 -> 133875 | G31: =E31-F31-98000 -> 303625
B32: Moderate | C32: 0.5 | D32: 10750 | E32: =210*C32*D32 -> 1128750 | F32: =E32*0.25 -> 282187.5 | G32: =E32-F32-98000 -> 748562.5
B33: Aggressive | C33: 0.65 | D33: 13350 | E33: =210*C33*D33 -> 1822275 | F33: =E33*0.25 -> 455568.75 | G33: =E33-F33-98000 -> 1268706.2
A35: WHAT IT COSTS TO UNLOCK
B36: Director of Venue Sales & Events: | D36: 85000 | E36: /year
B37: The only line required to make this real. Pays for itself in 6–8 events. Not currently in main budget.
A39: COMBINED PICTURE (Budget + Events Upside)
B40: Total Capitalization (no change): | D40: ='Production Budget'!F263 -> 6047850.3
B41: Investor Tier (55%): | D41: ='Production Budget'!F263*0.55 -> 3326317.7
B43: Show Weekly Contribution @ 80% capacity: | D43: =(('Seating Plan'!F26*0.8)+('Seating Plan'!G57*0.8))-(('Weekly Operating'!F124-0.03*'Seating Plan'!F26)+0.03*0.8*'Seating Plan'!F26) -> 9085
B44: Events Net Contribution (weekly avg):
B45: Conservative scenario: | D45: =G31/60 -> 5060.4167 | F45: =D43+D45 -> 14145.417 | G45: /wk total
B46: Moderate scenario: | D46: =G32/60 -> 12476.042 | F46: =D43+D46 -> 21561.042 | G46: /wk total
B47: Aggressive scenario: | D47: =G33/60 -> 21145.104 | F47: =D43+D47 -> 30230.104 | G47: /wk total
B49: Notes:
B50: • This sheet models the second-business opportunity from the dark days (Mon-Wed + weekday daytime).
B51: • Numbers are NOT included in the main Recoupment math — treat as upside scenario only.
B52: • Day rates derived from LA market comps for similar premium event venues.
B53: • Direct costs 25% accounts for event staffing, F&B for events, cleaning, utilities premium.
B54: • Director of Venue Sales position ($85K/yr) is the only required new hire to unlock this revenue.
B55: • A successful events program could shorten investor recoupment by 6-12 months at the moderate scenario.
B56: • Aggressive scenario (~65% utilization) would require sales/events team beyond the single director.
